/*    */ package jd.core.model.classfile.accessor;
/*    */ 
/*    */ public final class GetFieldAccessor
/*    */   extends Record
/*    */   implements Accessor
/*    */ {
/*    */   private final byte tag;
/*    */   private final String className;
/*    */   private final String fieldName;
/*    */   private final String fieldDescriptor;
/*    */   
/*    */   /* Error */
/*    */   @Override
/*    */   public final boolean equals(Object arg1)
/*    */   {
/*    */     // Byte code:
/*    */     //   0: aload_0
/*    */     //   1: aload_1
/*    */     //   2: invokedynamic 0 45 0 0
/*    */     //   7: ireturn
/*    */     // Line number table:
/*    */     //   Java source line #1	-> byte code offset #0
/*    */   }
/*    */   
/*    */   /* Error */
/*    */   @Override
/*    */   public final int hashCode()
/*    */   {
/*    */     // Byte code:
/*    */     //   0: aload_0
/*    */     //   1: invokedynamic 0 40 0 0
/*    */     //   6: ireturn
/*    */     // Line number table:
/*    */     //   Java source line #1	-> byte code offset #0
/*    */   }
/*    */   
/*    */   /* Error */
/*    */   @Override
/*    */   public final String toString()
/*    */   {
/*    */     // Byte code:
/*    */     //   0: aload_0
/*    */     //   1: invokedynamic 0 35 0 0
/*    */     //   6: areturn
/*    */     // Line number table:
/*    */     //   Java source line #1	-> byte code offset #0
/*    */   }
/*    */   
/*    */   public String fieldDescriptor()
/*    */   {
/* 19 */     return this.fieldDescriptor;
/*    */   }
/*    */   
/*    */   public String fieldName()
/*    */   {
/* 19 */     return this.fieldName;
/*    */   }
/*    */   
/*    */   public String className()
/*    */   {
/* 19 */     return this.className;
/*    */   }
/*    */   
/*    */   @Override
/*    */   public byte tag()
/*    */   {
/* 19 */     return this.tag;
/*    */   }
/*    */   
/*    */   public GetFieldAccessor(byte tag, String className, String fieldName, String fieldDescriptor)
/*    */   {
/* 19 */     this.tag = tag;this.className = className;this.fieldName = fieldName;this.fieldDescriptor = fieldDescriptor;
/*    */   }
/*    */ }
