// Byte code:
/*    */ //   0: aload_0
/*    */ //   1: dup
/*    */ //   2: getfield 17	jd/core/test/TableSwitch:inputValue	I
/*    */ //   5: dup_x1
/*    */ //   6: iconst_1
/*    */ //   7: iadd
/*    */ //   8: putfield 17	jd/core/test/TableSwitch:inputValue	I
/*    */ //   11: tableswitch	default:+70->81, -2:+48->59, -1:+70->81, 0:+70->81, 1:+37->48, 2:+48->59, 3:+59->70
/*    */ //   48: getstatic 19	java/lang/System:out	Ljava/io/PrintStream;
/*    */ //   51: ldc 25
/*    */ //   53: invokevirtual 27	java/io/PrintStream:println	(Ljava/lang/String;)V
/*    */ //   56: goto +33 -> 89
/*    */ //   59: getstatic 19	java/lang/System:out	Ljava/io/PrintStream;
/*    */ //   62: ldc 33
/*    */ //   64: invokevirtual 27	java/io/PrintStream:println	(Ljava/lang/String;)V
/*    */ //   67: goto +22 -> 89
/*    */ //   70: getstatic 19	java/lang/System:out	Ljava/io/PrintStream;
/*    */ //   73: ldc 35
/*    */ //   75: invokevirtual 27	java/io/PrintStream:println	(Ljava/lang/String;)V
/*    */ //   78: goto +11 -> 89
/*    */ //   81: new 37	java/lang/IllegalArgumentException
/*    */ //   84: dup
/*    */ //   85: invokespecial 39	java/lang/IllegalArgumentException:<init>	()V
/*    */ //   88: athrow
/*    */ //   89: return
/*    */ // Line number table:
/*    */ //   Java source line #10	-> byte code offset #0
/*    */ //   Java source line #12	-> byte code offset #48
/*    */ //   Java source line #13	-> byte code offset #56
/*    */ //   Java source line #15	-> byte code offset #59
/*    */ //   Java source line #16	-> byte code offset #67
/*    */ //   Java source line #18	-> byte code offset #70
/*    */ //   Java source line #19	-> byte code offset #78
/*    */ //   Java source line #21	-> byte code offset #81
/*    */ //   Java source line #23	-> byte code offset #89
/*    */ // Local variable table:
/*    */ //   start	length	slot	name	signature
/*    */ //   0	90	0	this	TableSwitch