// Byte code:
/*    */ //   0: aconst_null
/*    */ //   1: astore_2
/*    */ //   2: new 1	java/io/BufferedReader
/*    */ //   5: dup
/*    */ //   6: new 2	java/io/FileReader
/*    */ //   9: dup
/*    */ //   10: aload_1
/*    */ //   11: invokespecial 11	java/io/FileReader:<init>	(Ljava/io/File;)V
/*    */ //   14: invokespecial 12	java/io/BufferedReader:<init>	(Ljava/io/Reader;)V
/*    */ //   17: astore_2
/*    */ //   18: goto +11 -> 29
/*    */ //   21: getstatic 14	java/lang/System:out	Ljava/io/PrintStream;
/*    */ //   24: aload 5
/*    */ //   26: invokevirtual 16	java/io/PrintStream:println	(Ljava/lang/String;)V
/*    */ //   29: aload_2
/*    */ //   30: invokevirtual 17	java/io/BufferedReader:readLine	()Ljava/lang/String;
/*    */ //   33: dup
/*    */ //   34: astore 5
/*    */ //   36: ifnonnull -15 -> 21
/*    */ //   39: goto +13 -> 52
/*    */ //   42: astore 5
/*    */ //   44: aload 5
/*    */ //   46: invokevirtual 15	java/lang/Throwable:printStackTrace	()V
/*    */ //   49: goto +3 -> 52
/*    */ //   52: jsr +12 -> 64
/*    */ //   55: goto +34 -> 89
/*    */ //   58: astore_3
/*    */ //   59: jsr +5 -> 64
/*    */ //   62: aload_3
/*    */ //   63: athrow
/*    */ //   64: astore 4
/*    */ //   66: aload_2
/*    */ //   67: ifnull +20 -> 87
/*    */ //   70: aload_2
/*    */ //   71: invokevirtual 13	java/io/BufferedReader:close	()V
/*    */ //   74: goto +13 -> 87
/*    */ //   77: astore 5
/*    */ //   79: aload 5
/*    */ //   81: invokevirtual 15	java/lang/Throwable:printStackTrace	()V
/*    */ //   84: goto +3 -> 87
/*    */ //   87: ret 4
/*    */ //   89: return
/*    */ // Line number table:
/*    */ //   Java source line #11	-> byte code offset #0
/*    */ //   Java source line #12	-> byte code offset #2
/*    */ //   Java source line #13	-> byte code offset #2
/*    */ //   Java source line #15	-> byte code offset #18
/*    */ //   Java source line #16	-> byte code offset #21
/*    */ //   Java source line #15	-> byte code offset #29
/*    */ //   Java source line #12	-> byte code offset #39
/*    */ //   Java source line #18	-> byte code offset #42
/*    */ //   Java source line #19	-> byte code offset #44
/*    */ //   Java source line #12	-> byte code offset #49
/*    */ //   Java source line #21	-> byte code offset #66
/*    */ //   Java source line #22	-> byte code offset #70
/*    */ //   Java source line #23	-> byte code offset #70
/*    */ //   Java source line #22	-> byte code offset #74
/*    */ //   Java source line #24	-> byte code offset #77
/*    */ //   Java source line #25	-> byte code offset #79
/*    */ //   Java source line #22	-> byte code offset #84
/*    */ //   Java source line #12	-> byte code offset #87
/*    */ //   Java source line #10	-> byte code offset #89
/*    */ // Local variable table:
/*    */ //   start	length	slot	name	signature
/*    */ //   0	90	0	this	TryCatchFinallyBR
/*    */ //   0	90	1	paramFile	File
/*    */ //   1	70	2	localBufferedReader	BufferedReader
/*    */ //   58	5	3	localObject1	Object
/*    */ //   64	1	4	localObject2	Object
/*    */ //   24	11	5	str	String
/*    */ //   42	3	5	localException	Exception
/*    */ //   77	3	5	localIOException	IOException
/*    */ // Exception table:
/*    */ //   from	to	target	type
/*    */ //   2	39	42	java/lang/Exception
/*    */ //   2	52	58	finally
/*    */ //   70	74	77	java/io/IOException